dropbox_test_api/__init__.py
dropbox_test_api/api_helper.py
dropbox_test_api/configuration.py
dropbox_test_api/decorators.py
dropbox_test_api/dropbox_test_api_client.py
dropbox_test_api/controllers/__init__.py
dropbox_test_api/controllers/base_controller.py
dropbox_test_api/controllers/files_controller.py
dropbox_test_api/controllers/o_auth_authorization_controller.py
dropbox_test_api/exceptions/__init__.py
dropbox_test_api/exceptions/api_exception.py
dropbox_test_api/exceptions/o_auth_provider_exception.py
dropbox_test_api/http/__init__.py
dropbox_test_api/http/http_call_back.py
dropbox_test_api/http/http_client.py
dropbox_test_api/http/http_context.py
dropbox_test_api/http/http_method_enum.py
dropbox_test_api/http/http_request.py
dropbox_test_api/http/http_response.py
dropbox_test_api/http/requests_client.py
dropbox_test_api/http/auth/__init__.py
dropbox_test_api/http/auth/o_auth_2.py
dropbox_test_api/models/__init__.py
dropbox_test_api/models/o_auth_provider_error_enum.py
dropbox_test_api/models/o_auth_token.py
dropbox_test_api/models/response.py
dropbox_test_api-1.0.dist-info/LICENSE
dropbox_test_api-1.0.dist-info/METADATA
dropbox_test_api-1.0.dist-info/WHEEL
dropbox_test_api-1.0.dist-info/top_level.txt
dropbox_test_api-1.0.dist-info/RECORD
